LICENSE.txt
MANIFEST.in
README.rst
setup.py
utils/__init__.py
utils/bool.py
utils/cast.py
utils/dict.py
utils/exception.py
utils/list.py
utils/obj.py
utils/os.py
utils/process.py
utils/property.py
utils/string.py
utils/test/__init__.py
utils/test/test_dict.py
utils/test/test_exception.py
utils/test/test_list.py
utils/test/test_os.py
utils/test/test_process.py
utils/test/test_property.py
utilspy.egg-info/PKG-INFO
utilspy.egg-info/SOURCES.txt
utilspy.egg-info/dependency_links.txt
utilspy.egg-info/requires.txt
utilspy.egg-info/top_level.txt