Metadata-Version: 1.0
Name: utilspy
Version: 0.11.0
Summary: A number of useful utilities that don't seem to exist elsewhere
Home-page: https://github.com/HubSpot/utilspy
Author: prior
Author-email: mprior@hubspot.com
License: LICENSE.txt
Download-URL: https://github.com/HubSpot/utilspy/tarball/v0.11.0
Platform: any
